ceurws/__init__.py
ceurws/ceur_ws.py
ceurws/ceur_ws_web_cmd.py
ceurws/config.py
ceurws/dblp.py
ceurws/endpoints.py
ceurws/indexparser.py
ceurws/location.py
ceurws/loctime.py
ceurws/namedqueries.py
ceurws/papertocparser.py
ceurws/sql_cache.py
ceurws/textparser.py
ceurws/urn.py
ceurws/version.py
ceurws/view.py
ceurws/volume_neo4j.py
ceurws/volume_view.py
ceurws/volumeparser.py
ceurws/webserver.py
ceurws/wikidata_view.py
ceurws/wikidatasync.py
ceurws/workshop.py
ceurws/models/__init__.py
ceurws/models/ceur.py
ceurws/models/dblp.py
ceurws/models/dblp2.py
ceurws/resources/queries/ceurws.yaml
ceurws/resources/queries/dblp.yaml
ceurws/services/__init__.py
ceurws/services/entity_fishing.py
ceurws/services/opentapioca.py
ceurws/utils/__init__.py
ceurws/utils/download.py
ceurws/utils/webscrape.py
pyceurmake-0.4.3.dist-info/METADATA
pyceurmake-0.4.3.dist-info/WHEEL
pyceurmake-0.4.3.dist-info/entry_points.txt
pyceurmake-0.4.3.dist-info/licenses/LICENSE
pyceurmake-0.4.3.dist-info/RECORD
